ecstremity/__init__.py
ecstremity/component.py
ecstremity/engine.py
ecstremity/entity.py
ecstremity/entity_event.py
ecstremity/prefab.py
ecstremity/query.py
ecstremity/registries/__init__.py
ecstremity/registries/component_registry.py
ecstremity/registries/entity_registry.py
ecstremity/registries/prefab_registry.py
ecstremity/registries/query_registry.py
ecstremity/registries/registry.py
ecstremity-1.0.4.dist-info/LICENSE
ecstremity-1.0.4.dist-info/METADATA
ecstremity-1.0.4.dist-info/WHEEL
ecstremity-1.0.4.dist-info/top_level.txt
ecstremity-1.0.4.dist-info/RECORD
