Metadata-Version: 2.1
Name: ecstremity
Version: 1.0.4
Summary: An ECS Library based on the JavaScript geotic library.
Home-page: https://github.com/krummja/ECStremity
Author: Jonathan Crum
Author-email: crumja4@gmail.com
License: MIT
Platform: UNKNOWN
Requires-Python: >=3.8.5
Requires-Dist: uuid
